LICENSE
spatial_kde/__init__.py
spatial_kde/cli.py
spatial_kde/kde.py
spatial_kde/kernels.py
spatial_kde/utils.py
spatial_kde-0.1.0.dist-info/entry_points.txt
spatial_kde-0.1.0.dist-info/LICENSE
spatial_kde-0.1.0.dist-info/WHEEL
spatial_kde-0.1.0.dist-info/METADATA
spatial_kde-0.1.0.dist-info/RECORD
