Metadata-Version: 2.1
Name: spatial-kde
Version: 0.1.0
Summary: Create Spatial Kernel Density / Heatmap (as a numpy array or raster) from point based vector data
Home-page: https://github.com/mblackgeo/spatial-kde
Keywords: raster,vector,kernel density,heatmap
Author: mblackgeo
Author-email: 18327836+mblackgeo@users.noreply.github.com
Requires-Python: >=3.8,<3.11
Classifier: Programming Language :: Python :: 3
Classifier: Programming Language :: Python :: 3.10
Classifier: Programming Language :: Python :: 3.8
Classifier: Programming Language :: Python :: 3.9
Requires-Dist: Shapely (>=1.8.0,<2.0.0)
Requires-Dist: geopandas (>=0.10.2,<0.11.0)
Requires-Dist: numpy (>=1.22.1,<2.0.0)
Requires-Dist: pandarallel (>=1.5.4,<2.0.0)
Requires-Dist: pandas (>=1.4.0,<2.0.0)
Requires-Dist: pyproj (>=3.3.0,<4.0.0)
Requires-Dist: rasterio (>=1.2.10,<2.0.0)
Requires-Dist: scipy (>=1.7.3,<2.0.0)
Requires-Dist: typer (>=0.4.0,<0.5.0)
Project-URL: Repository, https://github.com/mblackgeo/spatial-kde
